Metadata-Version: 2.1
Name: Topsis-Snehil-101903064
Version: 2.0.0
Summary: Implements topsis on the given input data file and generates topsis score and ranks accordingly.
Home-page: https://github.com/Snehil-21/Topsis-Snehil-101903064
Author: Snehil Gupta
Author-email: sgupta2_be19@thapar.edu
License: MIT
Platform: UNKNOWN
Classifier: License :: OSI Approved :: MIT License
Classifier: Programming Language :: Python :: 3.8
Classifier: Programming Language :: Python :: 3.9
Classifier: Programming Language :: Python :: 3.10
License-File: LICENSE.txt
Requires-Dist: pandas
